nonebot_plugin_ddcheck/__init__.py
nonebot_plugin_ddcheck/config.py
nonebot_plugin_ddcheck/data_source.py
nonebot_plugin_ddcheck/template/info.html
nonebot_plugin_ddcheck-0.4.3.dist-info/LICENSE
nonebot_plugin_ddcheck-0.4.3.dist-info/METADATA
nonebot_plugin_ddcheck-0.4.3.dist-info/WHEEL
nonebot_plugin_ddcheck-0.4.3.dist-info/RECORD
