Metadata-Version: 2.1
Name: nonebot_plugin_ddcheck
Version: 0.4.3
Summary: Nonebot2 成分姬插件
Home-page: https://github.com/noneplugin/nonebot-plugin-ddcheck
License: MIT
Author: meetwq
Author-email: meetwq@gmail.com
Requires-Python: >=3.9,<4.0
Classifier: License :: OSI Approved :: MIT License
Classifier: Programming Language :: Python :: 3
Classifier: Programming Language :: Python :: 3.9
Classifier: Programming Language :: Python :: 3.10
Classifier: Programming Language :: Python :: 3.11
Classifier: Programming Language :: Python :: 3.12
Classifier: Programming Language :: Python :: 3.13
Requires-Dist: Jinja2 (>=3.0.0,<4.0.0)
Requires-Dist: httpx (>=0.20.0,<1.0.0)
Requires-Dist: nonebot-plugin-alconna (>=0.46.3,<1.0.0)
Requires-Dist: nonebot-plugin-apscheduler (>=0.4.0,<1.0.0)
Requires-Dist: nonebot-plugin-htmlrender (>=0.4.0,<0.5.0)
Requires-Dist: nonebot-plugin-localstore (>=0.6.0,<1.0.0)
Requires-Dist: nonebot2 (>=2.3.0,<3.0.0)
Project-URL: Repository, https://github.com/noneplugin/nonebot-plugin-ddcheck
